wcpan/logging/__init__.py
wcpan/logging/builder.py
wcpan/logging/const.py
wcpan/logging/formatter.py
wcpan/logging/py.typed
wcpan/logging/types.py
wcpan_logging-2.1.0.dist-info/LICENSE.txt
wcpan_logging-2.1.0.dist-info/METADATA
wcpan_logging-2.1.0.dist-info/WHEEL
wcpan_logging-2.1.0.dist-info/RECORD
